{
	"textures": {
		"0": "animated_java:item/eclael/eclael"
	},
	"elements": [
		{
			"from": [
				7,
				2,
				6.125
			],
			"to": [
				7,
				7.75,
				9.875
			],
			"rotation": {
				"angle": 0,
				"axis": "y",
				"origin": [
					7,
					8,
					8
				]
			},
			"faces": {
				"east": {
					"uv": [
						9.625,
						1.875,
						9.125,
						2.5
					],
					"texture": "#0"
				},
				"west": {
					"uv": [
						9.625,
						1.875,
						9.125,
						2.5
					],
					"texture": "#0"
				}
			}
		}
	],
	"display": {
		"head": {
			"rotation": [
				0,
				180,
				0
			]
		}
	}
}