{
	"credit": "Made with Blockbench",
	"texture_size": [32, 32],
	"textures": {
		"0": "item/artifact/carrot_on_a_stick/1065/texture",
		"particle": "item/artifact/carrot_on_a_stick/1065/texture"
	},
	"elements": [
		{
			"from": [7.788, 1.37946, 13.61921],
			"to": [8.287, 3.37846, 13.86896],
			"rotation": {"angle": -45, "axis": "x", "origin": [8, 8, 9]},
			"faces": {
				"north": {"uv": [10, 10.5, 10.5, 11.5], "texture": "#0"},
				"east": {"uv": [10.5, 10, 11, 11], "texture": "#0"},
				"south": {"uv": [11, 0.5, 11.5, 1.5], "texture": "#0"},
				"west": {"uv": [11, 1.5, 11.5, 2.5], "texture": "#0"},
				"up": {"uv": [9, 7.5, 8.5, 7], "texture": "#0"},
				"down": {"uv": [11.5, 2.5, 11, 3], "texture": "#0"}
			}
		},
		{
			"from": [7.7875, 3.65061, 15.80124],
			"to": [8.2875, 3.90062, 17.30124],
			"rotation": {"angle": -22.5, "axis": "x", "origin": [8, 8, 9]},
			"faces": {
				"north": {"uv": [2, 11.5, 2.5, 12], "texture": "#0"},
				"east": {"uv": [10.5, 3, 11.5, 3.5], "texture": "#0"},
				"south": {"uv": [2.5, 11.5, 3, 12], "texture": "#0"},
				"west": {"uv": [10.5, 8, 11.5, 8.5], "texture": "#0"},
				"up": {"uv": [11.5, 5, 11, 4], "texture": "#0"},
				"down": {"uv": [5.5, 11, 5, 12], "texture": "#0"}
			}
		},
		{
			"from": [7.8375, 7.04709, 17.12451],
			"to": [8.0875, 8.04709, 17.37451],
			"rotation": {"angle": 0, "axis": "x", "origin": [8, 8, 9]},
			"faces": {
				"north": {"uv": [11.5, 2.5, 12, 3], "texture": "#0"},
				"east": {"uv": [11.5, 3, 12, 3.5], "texture": "#0"},
				"south": {"uv": [11.5, 3.5, 12, 4], "texture": "#0"},
				"west": {"uv": [11.5, 4, 12, 4.5], "texture": "#0"},
				"up": {"uv": [12, 5, 11.5, 4.5], "texture": "#0"},
				"down": {"uv": [12, 5, 11.5, 5.5], "texture": "#0"}
			}
		},
		{
			"from": [7.5425, 7.60971, 11.25369],
			"to": [8.5325, 8.10471, 17.23869],
			"rotation": {"angle": 0, "axis": "x", "origin": [8, 8, 9]},
			"faces": {
				"north": {"uv": [11.5, 5.5, 12, 6], "texture": "#0"},
				"east": {"uv": [7.5, 1.5, 10.5, 2], "texture": "#0"},
				"south": {"uv": [11.5, 6, 12, 6.5], "texture": "#0"},
				"west": {"uv": [6, 7.5, 9, 8], "texture": "#0"},
				"up": {"uv": [6.5, 11, 6, 8], "texture": "#0"},
				"down": {"uv": [7, 8, 6.5, 11], "texture": "#0"}
			}
		},
		{
			"from": [7.543, 4.79611, 16.00031],
			"to": [8.53201, 6.77611, 18.72207],
			"rotation": {"angle": -22.5, "axis": "x", "origin": [8.00038, 8.01122, 9.08583]},
			"faces": {
				"north": {"uv": [11, 5, 11.5, 6], "texture": "#0"},
				"east": {"uv": [8, 4, 9.5, 5], "texture": "#0"},
				"south": {"uv": [5.5, 11, 6, 12], "texture": "#0"},
				"west": {"uv": [8, 5, 9.5, 6], "texture": "#0"},
				"up": {"uv": [10.5, 3.5, 10, 2], "texture": "#0"},
				"down": {"uv": [10.5, 7, 10, 8.5], "texture": "#0"}
			}
		},
		{
			"from": [7.54245, 8.28716, 0.58331],
			"to": [8.53255, 9.27726, 17.90906],
			"rotation": {"angle": 0, "axis": "y", "origin": [8.00038, 8.00782, 9.00246]},
			"faces": {
				"north": {"uv": [11.5, 9.5, 12, 10], "texture": "#0"},
				"east": {"uv": [0, 2, 9, 2.5], "texture": "#0"},
				"south": {"uv": [10, 11.5, 10.5, 12], "texture": "#0"},
				"west": {"uv": [0, 2.5, 9, 3], "texture": "#0"},
				"up": {"uv": [0.5, 12, 0, 3], "texture": "#0"},
				"down": {"uv": [1, 3, 0.5, 12], "texture": "#0"}
			}
		},
		{
			"from": [7.53745, 9.28216, 0.49581],
			"to": [8.53755, 10.03226, 18.49656],
			"rotation": {"angle": 0, "axis": "y", "origin": [8, 8, 9]},
			"faces": {
				"north": {"uv": [11.5, 10, 12, 10.5], "texture": "#0"},
				"east": {"uv": [1, 3, 10, 3.5], "texture": "#0"},
				"south": {"uv": [11.5, 10.5, 12, 11], "texture": "#0"},
				"west": {"uv": [1, 3.5, 10, 4], "texture": "#0"},
				"up": {"uv": [1.5, 13, 1, 4], "texture": "#0"},
				"down": {"uv": [2, 4, 1.5, 13], "texture": "#0"}
			}
		},
		{
			"from": [7.7875, 9.35721, -7.62881],
			"to": [8.2875, 9.85721, 0.87119],
			"rotation": {"angle": 0, "axis": "x", "origin": [8, 8.75, 7]},
			"faces": {
				"north": {"uv": [11.5, 6.5, 12, 7], "texture": "#0"},
				"east": {"uv": [4, 7, 8.5, 7.5], "texture": "#0"},
				"south": {"uv": [11.5, 7, 12, 7.5], "texture": "#0"},
				"west": {"uv": [7.5, 0, 12, 0.5], "texture": "#0"},
				"up": {"uv": [4.5, 12, 4, 7.5], "texture": "#0"},
				"down": {"uv": [5, 7.5, 4.5, 12], "texture": "#0"}
			}
		},
		{
			"from": [7.7875, 8.60721, -5.62881],
			"to": [8.2875, 9.10721, 0.87119],
			"rotation": {"angle": 0, "axis": "x", "origin": [8, 8, 9]},
			"faces": {
				"north": {"uv": [11.5, 9, 12, 9.5], "texture": "#0"},
				"east": {"uv": [7.5, 0.5, 11, 1], "texture": "#0"},
				"south": {"uv": [9.5, 11.5, 10, 12], "texture": "#0"},
				"west": {"uv": [7.5, 1, 11, 1.5], "texture": "#0"},
				"up": {"uv": [5.5, 11, 5, 7.5], "texture": "#0"},
				"down": {"uv": [6, 7.5, 5.5, 11], "texture": "#0"}
			}
		},
		{
			"from": [7.53788, 7.02337, 16.15396],
			"to": [8.53713, 9.02237, 21.40221],
			"rotation": {"angle": 22.5, "axis": "x", "origin": [8.16251, 7.77287, 18.77809]},
			"faces": {
				"north": {"uv": [6, 11, 6.5, 12], "texture": "#0"},
				"east": {"uv": [5.5, 4, 8, 5], "texture": "#0"},
				"south": {"uv": [11, 6, 11.5, 7], "texture": "#0"},
				"west": {"uv": [5.5, 5, 8, 6], "texture": "#0"},
				"up": {"uv": [8.5, 11.5, 8, 9], "texture": "#0"},
				"down": {"uv": [9, 9, 8.5, 11.5], "texture": "#0"}
			}
		},
		{
			"from": [7.54288, 7.71265, 19.62918],
			"to": [8.53213, 10.18666, 21.85494],
			"rotation": {"angle": -45, "axis": "x", "origin": [8.16126, 8.45465, 22.22706]},
			"faces": {
				"north": {"uv": [6.5, 11, 7, 12], "texture": "#0"},
				"east": {"uv": [9, 2, 10, 3], "texture": "#0"},
				"south": {"uv": [11, 7, 11.5, 8], "texture": "#0"},
				"west": {"uv": [9, 7, 10, 8], "texture": "#0"},
				"up": {"uv": [11.5, 10, 11, 9], "texture": "#0"},
				"down": {"uv": [11.5, 10, 11, 11], "texture": "#0"}
			}
		},
		{
			"from": [7.54787, 8.05954, 24.64128],
			"to": [8.52714, 10.26356, 26.59956],
			"rotation": {"angle": -45, "axis": "x", "origin": [8.16001, 8.79405, 27.21292]},
			"faces": {
				"north": {"uv": [10.5, 11, 11, 12], "texture": "#0"},
				"east": {"uv": [9.5, 4, 10.5, 5], "texture": "#0"},
				"south": {"uv": [11, 11, 11.5, 12], "texture": "#0"},
				"west": {"uv": [9.5, 5, 10.5, 6], "texture": "#0"},
				"up": {"uv": [12, 1.5, 11.5, 0.5], "texture": "#0"},
				"down": {"uv": [12, 1.5, 11.5, 2.5], "texture": "#0"}
			}
		},
		{
			"from": [7.53788, 7.54597, 20.52826],
			"to": [8.53713, 8.79422, 23.52726],
			"rotation": {"angle": -22.5, "axis": "x", "origin": [8.16251, 10.17009, 22.27776]},
			"faces": {
				"north": {"uv": [11.5, 8, 12, 8.5], "texture": "#0"},
				"east": {"uv": [10, 3.5, 11.5, 4], "texture": "#0"},
				"south": {"uv": [8.5, 11.5, 9, 12], "texture": "#0"},
				"west": {"uv": [10, 8.5, 11.5, 9], "texture": "#0"},
				"up": {"uv": [10.5, 10.5, 10, 9], "texture": "#0"},
				"down": {"uv": [11, 1.5, 10.5, 3], "texture": "#0"}
			}
		},
		{
			"from": [7.53788, 7.64597, 21.86774],
			"to": [8.53713, 8.89422, 27.86674],
			"rotation": {"angle": 22.5, "axis": "x", "origin": [8.16251, 10.27009, 23.11724]},
			"faces": {
				"north": {"uv": [11.5, 8.5, 12, 9], "texture": "#0"},
				"east": {"uv": [7, 8, 10, 8.5], "texture": "#0"},
				"south": {"uv": [9, 11.5, 9.5, 12], "texture": "#0"},
				"west": {"uv": [7, 8.5, 10, 9], "texture": "#0"},
				"up": {"uv": [7.5, 12, 7, 9], "texture": "#0"},
				"down": {"uv": [8, 9, 7.5, 12], "texture": "#0"}
			}
		},
		{
			"from": [7.54288, 6.04066, 26.52849],
			"to": [8.53213, 8.51566, 31.97251],
			"rotation": {"angle": 0, "axis": "x", "origin": [8.16126, 8.63855, 30.55832]},
			"faces": {
				"north": {"uv": [10.5, 4, 11, 5.5], "texture": "#0"},
				"east": {"uv": [3, 4, 5.5, 5.5], "texture": "#0"},
				"south": {"uv": [10.5, 5.5, 11, 7], "texture": "#0"},
				"west": {"uv": [3, 5.5, 5.5, 7], "texture": "#0"},
				"up": {"uv": [9.5, 11.5, 9, 9], "texture": "#0"},
				"down": {"uv": [10, 9, 9.5, 11.5], "texture": "#0"}
			}
		},
		{
			"from": [7.53788, 8.02337, 17.15396],
			"to": [8.53713, 9.52337, 32],
			"rotation": {"angle": 0, "axis": "y", "origin": [8.16251, 9.02287, 19.77809]},
			"faces": {
				"north": {"uv": [10.5, 7, 11, 8], "texture": "#0"},
				"east": {"uv": [0, 0, 7.5, 1], "texture": "#0"},
				"south": {"uv": [10.5, 9, 11, 10], "texture": "#0"},
				"west": {"uv": [0, 1, 7.5, 2], "texture": "#0"},
				"up": {"uv": [2.5, 11.5, 2, 4], "texture": "#0"},
				"down": {"uv": [3, 4, 2.5, 11.5], "texture": "#0"}
			}
		},
		{
			"from": [7.6625, 7.78221, 6.74619],
			"to": [8.4125, 9.03221, 16.49619],
			"rotation": {"angle": 0, "axis": "x", "origin": [8, 8, 9]},
			"faces": {
				"north": {"uv": [11.5, 7.5, 12, 8], "texture": "#0"},
				"east": {"uv": [5.5, 6, 10.5, 6.5], "texture": "#0"},
				"south": {"uv": [8, 11.5, 8.5, 12], "texture": "#0"},
				"west": {"uv": [5.5, 6.5, 10.5, 7], "texture": "#0"},
				"up": {"uv": [3.5, 12, 3, 7], "texture": "#0"},
				"down": {"uv": [4, 7, 3.5, 12], "texture": "#0"}
			}
		}
	],
	"gui_light": "front",
	"display": {
		"thirdperson_righthand": {
			"translation": [-1, 0.5, -8],
			"scale": [0.88, 0.88, 0.88]
		},
		"thirdperson_lefthand": {
			"rotation": [-17, -66, 100],
			"translation": [2, -6.75, 6]
		},
		"firstperson_righthand": {
			"rotation": [0, -10.25, 0],
			"translation": [-3.75, 6.5, 1.25],
			"scale": [0.66, 0.66, 0.66]
		},
		"firstperson_lefthand": {
			"rotation": [0, -10.25, 0],
			"translation": [-3.75, 6.5, 1.25],
			"scale": [0.66, 0.66, 0.66]
		},
		"ground": {
			"rotation": [24, 0, 0],
			"translation": [0, 0.25, 0],
			"scale": [0.43, 0.43, 0.43]
		},
		"gui": {
			"rotation": [90, -47.75, 93],
			"translation": [2.25, 1.5, 0],
			"scale": [0.55, 0.55, 0.55]
		},
		"head": {
			"translation": [0, -3.25, -29],
			"scale": [4, 4, 4]
		},
		"fixed": {
			"rotation": [-180, 90, -180],
			"translation": [-2, 0, 0],
			"scale": [0.49, 0.49, 0.49]
		}
	}
}