{
	"textures": {
		"1": "animated_java:item/lexiel/texture"
	},
	"elements": [
		{
			"from": [
				7.026378378378379,
				5.0889890786339596,
				9.91227231066622
			],
			"to": [
				8.973621621621621,
				10.926826916471798,
				10.560920959314869
			],
			"rotation": {
				"angle": 0,
				"axis": "y",
				"origin": [
					8,
					5.0889890786339596,
					9.91227231066622
				]
			},
			"faces": {
				"north": {
					"uv": [
						2.5,
						2.25,
						3.25,
						0
					],
					"texture": "#1",
					"tintindex": 0
				},
				"east": {
					"uv": [
						5.25,
						2.25,
						7.5,
						2
					],
					"rotation": 270,
					"texture": "#1",
					"tintindex": 0
				},
				"south": {
					"uv": [
						2.5,
						2.25,
						3.25,
						4.5
					],
					"rotation": 180,
					"texture": "#1",
					"tintindex": 0
				},
				"west": {
					"uv": [
						5.25,
						2.5,
						7.5,
						2.25
					],
					"rotation": 90,
					"texture": "#1",
					"tintindex": 0
				},
				"up": {
					"uv": [
						6.5,
						3.25,
						7.25,
						3
					],
					"rotation": 180,
					"texture": "#1",
					"tintindex": 0
				},
				"down": {
					"uv": [
						6.25,
						6.75,
						7,
						6.5
					],
					"texture": "#1",
					"tintindex": 0
				}
			}
		},
		{
			"from": [
				7.027027027027027,
				7.034935024579905,
				9.26362366201757
			],
			"to": [
				8.972972972972974,
				8.98088097052585,
				9.91227231066622
			],
			"rotation": {
				"angle": 0,
				"axis": "y",
				"origin": [
					8,
					3.143043132688013,
					9.26362366201757
				]
			},
			"faces": {
				"north": {
					"uv": [
						5.25,
						3.25,
						6,
						2.5
					],
					"texture": "#1",
					"tintindex": 0
				},
				"east": {
					"uv": [
						6.75,
						0.5,
						7.5,
						0.25
					],
					"rotation": 270,
					"texture": "#1",
					"tintindex": 0
				},
				"south": {
					"uv": [
						3,
						5.25,
						3.75,
						6
					],
					"rotation": 180,
					"texture": "#1",
					"tintindex": 0
				},
				"west": {
					"uv": [
						6.75,
						1,
						7.5,
						0.75
					],
					"rotation": 90,
					"texture": "#1",
					"tintindex": 0
				},
				"up": {
					"uv": [
						6.75,
						0.25,
						7.5,
						0
					],
					"rotation": 180,
					"texture": "#1",
					"tintindex": 0
				},
				"down": {
					"uv": [
						6.75,
						0.75,
						7.5,
						0.5
					],
					"texture": "#1",
					"tintindex": 0
				}
			}
		},
		{
			"from": [
				7.351351351351351,
				6.710610700255581,
				10.560920959314869
			],
			"to": [
				8.64864864864865,
				9.305205294850175,
				11.20956960796352
			],
			"rotation": {
				"angle": 0,
				"axis": "y",
				"origin": [
					8.324324324324325,
					3.4673674570123376,
					9.26362366201757
				]
			},
			"faces": {
				"north": {
					"uv": [
						5.25,
						5.5,
						5.75,
						4.5
					],
					"texture": "#1",
					"tintindex": 0
				},
				"east": {
					"uv": [
						6,
						4.5,
						7,
						4.25
					],
					"rotation": 270,
					"texture": "#1",
					"tintindex": 0
				},
				"south": {
					"uv": [
						5.25,
						5.5,
						5.75,
						6.5
					],
					"rotation": 180,
					"texture": "#1",
					"tintindex": 0
				},
				"west": {
					"uv": [
						0.5,
						6.5,
						1.5,
						6.25
					],
					"rotation": 90,
					"texture": "#1",
					"tintindex": 0
				},
				"up": {
					"uv": [
						4.75,
						7,
						5.25,
						6.75
					],
					"rotation": 180,
					"texture": "#1",
					"tintindex": 0
				},
				"down": {
					"uv": [
						1,
						7.25,
						1.5,
						7
					],
					"texture": "#1",
					"tintindex": 0
				}
			}
		},
		{
			"from": [
				7.351351351351351,
				10.926826916471798,
				9.91227231066622
			],
			"to": [
				8.64864864864865,
				11.575475565120446,
				10.560920959314869
			],
			"rotation": {
				"angle": 0,
				"axis": "y",
				"origin": [
					8,
					5.0889890786339596,
					9.91227231066622
				]
			},
			"faces": {
				"north": {
					"uv": [
						4,
						7.25,
						4.5,
						7
					],
					"texture": "#1",
					"tintindex": 0
				},
				"east": {
					"uv": [
						4,
						6.75,
						4.25,
						6.5
					],
					"rotation": 270,
					"texture": "#1",
					"tintindex": 0
				},
				"south": {
					"uv": [
						7,
						4.25,
						7.5,
						4.5
					],
					"rotation": 180,
					"texture": "#1",
					"tintindex": 0
				},
				"west": {
					"uv": [
						7.5,
						5.75,
						7.75,
						5.5
					],
					"rotation": 90,
					"texture": "#1",
					"tintindex": 0
				},
				"up": {
					"uv": [
						7,
						3,
						7.5,
						2.75
					],
					"rotation": 180,
					"texture": "#1",
					"tintindex": 0
				},
				"down": {
					"uv": [
						3.5,
						7.25,
						4,
						7
					],
					"texture": "#1",
					"tintindex": 0
				}
			}
		},
		{
			"from": [
				7.351351351351351,
				4.44034042998531,
				9.91227231066622
			],
			"to": [
				8.64864864864865,
				5.0889890786339596,
				10.560920959314869
			],
			"rotation": {
				"angle": 0,
				"axis": "y",
				"origin": [
					8,
					6.386286375931257,
					9.91227231066622
				]
			},
			"faces": {
				"north": {
					"uv": [
						5.5,
						7.25,
						6,
						7
					],
					"texture": "#1",
					"tintindex": 0
				},
				"east": {
					"uv": [
						5.75,
						7.75,
						6,
						7.5
					],
					"rotation": 270,
					"texture": "#1",
					"tintindex": 0
				},
				"south": {
					"uv": [
						6,
						7,
						6.5,
						7.25
					],
					"rotation": 180,
					"texture": "#1",
					"tintindex": 0
				},
				"west": {
					"uv": [
						7.5,
						6,
						7.75,
						5.75
					],
					"rotation": 90,
					"texture": "#1",
					"tintindex": 0
				},
				"up": {
					"uv": [
						4.5,
						7.25,
						5,
						7
					],
					"rotation": 180,
					"texture": "#1",
					"tintindex": 0
				},
				"down": {
					"uv": [
						5,
						7.25,
						5.5,
						7
					],
					"texture": "#1",
					"tintindex": 0
				}
			}
		},
		{
			"from": [
				7.675675675675675,
				5.0889890786339596,
				9.26362366201757
			],
			"to": [
				8.324324324324325,
				10.926826916471798,
				9.91227231066622
			],
			"rotation": {
				"angle": 0,
				"axis": "y",
				"origin": [
					8,
					5.0889890786339596,
					9.91227231066622
				]
			},
			"faces": {
				"north": {
					"uv": [
						2,
						7.5,
						2.25,
						5.25
					],
					"texture": "#1",
					"tintindex": 0
				},
				"east": {
					"uv": [
						5.25,
						3.5,
						7.5,
						3.25
					],
					"rotation": 270,
					"texture": "#1",
					"tintindex": 0
				},
				"south": {
					"uv": [
						2.25,
						5.25,
						2.5,
						7.5
					],
					"rotation": 180,
					"texture": "#1",
					"tintindex": 0
				},
				"west": {
					"uv": [
						5.25,
						3.75,
						7.5,
						3.5
					],
					"rotation": 90,
					"texture": "#1",
					"tintindex": 0
				},
				"up": {
					"uv": [
						6,
						7.75,
						6.25,
						7.5
					],
					"rotation": 180,
					"texture": "#1",
					"tintindex": 0
				},
				"down": {
					"uv": [
						7.5,
						6.25,
						7.75,
						6
					],
					"texture": "#1",
					"tintindex": 0
				}
			}
		},
		{
			"from": [
				7.027027027027027,
				8.332232321877203,
				7.317677716071625
			],
			"to": [
				8.972972972972974,
				8.98088097052585,
				9.91227231066622
			],
			"rotation": {
				"angle": 22.5,
				"axis": "x",
				"origin": [
					8,
					8.007907997552879,
					10.236596634990544
				]
			},
			"faces": {
				"north": {
					"uv": [
						6.75,
						1.25,
						7.5,
						1
					],
					"texture": "#1",
					"tintindex": 0
				},
				"east": {
					"uv": [
						1.5,
						7.25,
						1.75,
						6.25
					],
					"rotation": 270,
					"texture": "#1",
					"tintindex": 0
				},
				"south": {
					"uv": [
						6.75,
						1.25,
						7.5,
						1.5
					],
					"rotation": 180,
					"texture": "#1",
					"tintindex": 0
				},
				"west": {
					"uv": [
						1.75,
						7.25,
						2,
						6.25
					],
					"rotation": 90,
					"texture": "#1",
					"tintindex": 0
				},
				"up": {
					"uv": [
						5.25,
						1,
						6,
						0
					],
					"rotation": 180,
					"texture": "#1",
					"tintindex": 0
				},
				"down": {
					"uv": [
						0.5,
						6.25,
						1.25,
						5.25
					],
					"texture": "#1",
					"tintindex": 0
				}
			}
		},
		{
			"from": [
				7.351351351351351,
				8.98088097052585,
				7.966326364720274
			],
			"to": [
				8.64864864864865,
				9.6295296191745,
				9.91227231066622
			],
			"rotation": {
				"angle": 22.5,
				"axis": "x",
				"origin": [
					8,
					8.007907997552879,
					10.236596634990544
				]
			},
			"faces": {
				"north": {
					"uv": [
						6.5,
						7.25,
						7,
						7
					],
					"texture": "#1",
					"tintindex": 0
				},
				"east": {
					"uv": [
						3,
						5.25,
						3.25,
						4.5
					],
					"rotation": 270,
					"texture": "#1",
					"tintindex": 0
				},
				"south": {
					"uv": [
						7,
						6.5,
						7.5,
						6.75
					],
					"rotation": 180,
					"texture": "#1",
					"tintindex": 0
				},
				"west": {
					"uv": [
						4.5,
						6,
						4.75,
						5.25
					],
					"rotation": 90,
					"texture": "#1",
					"tintindex": 0
				},
				"up": {
					"uv": [
						5.75,
						5.25,
						6.25,
						4.5
					],
					"rotation": 180,
					"texture": "#1",
					"tintindex": 0
				},
				"down": {
					"uv": [
						5.75,
						6,
						6.25,
						5.25
					],
					"texture": "#1",
					"tintindex": 0
				}
			}
		},
		{
			"from": [
				7.351351351351351,
				8.332232321877203,
				6.669029067422976
			],
			"to": [
				8.64864864864865,
				8.98088097052585,
				7.317677716071625
			],
			"rotation": {
				"angle": 22.5,
				"axis": "x",
				"origin": [
					8,
					8.007907997552879,
					10.236596634990544
				]
			},
			"faces": {
				"north": {
					"uv": [
						1.5,
						7.5,
						2,
						7.25
					],
					"texture": "#1",
					"tintindex": 0
				},
				"east": {
					"uv": [
						6.25,
						7.75,
						6.5,
						7.5
					],
					"rotation": 270,
					"texture": "#1",
					"tintindex": 0
				},
				"south": {
					"uv": [
						7.25,
						3,
						7.75,
						3.25
					],
					"rotation": 180,
					"texture": "#1",
					"tintindex": 0
				},
				"west": {
					"uv": [
						7.5,
						6.5,
						7.75,
						6.25
					],
					"rotation": 90,
					"texture": "#1",
					"tintindex": 0
				},
				"up": {
					"uv": [
						7,
						7.25,
						7.5,
						7
					],
					"rotation": 180,
					"texture": "#1",
					"tintindex": 0
				},
				"down": {
					"uv": [
						1,
						7.5,
						1.5,
						7.25
					],
					"texture": "#1",
					"tintindex": 0
				}
			}
		},
		{
			"from": [
				7.351351351351351,
				8.98088097052585,
				10.074434472828383
			],
			"to": [
				8.64864864864865,
				9.6295296191745,
				11.371731770125681
			],
			"rotation": {
				"angle": -22.5,
				"axis": "x",
				"origin": [
					8,
					9.6295296191745,
					8.939299337693246
				]
			},
			"faces": {
				"north": {
					"uv": [
						4,
						7.5,
						4.5,
						7.25
					],
					"texture": "#1",
					"tintindex": 0
				},
				"east": {
					"uv": [
						3.5,
						7.75,
						3.75,
						7.25
					],
					"rotation": 270,
					"texture": "#1",
					"tintindex": 0
				},
				"south": {
					"uv": [
						4.5,
						7.25,
						5,
						7.5
					],
					"rotation": 180,
					"texture": "#1",
					"tintindex": 0
				},
				"west": {
					"uv": [
						3.75,
						7.75,
						4,
						7.25
					],
					"rotation": 90,
					"texture": "#1",
					"tintindex": 0
				},
				"up": {
					"uv": [
						6.25,
						5,
						6.75,
						4.5
					],
					"rotation": 180,
					"texture": "#1",
					"tintindex": 0
				},
				"down": {
					"uv": [
						6.25,
						5.5,
						6.75,
						5
					],
					"texture": "#1",
					"tintindex": 0
				}
			}
		},
		{
			"from": [
				7.027027027027027,
				8.332232321877203,
				10.074434472828383
			],
			"to": [
				8.972972972972974,
				8.98088097052585,
				11.371731770125681
			],
			"rotation": {
				"angle": -22.5,
				"axis": "x",
				"origin": [
					8,
					9.6295296191745,
					8.939299337693246
				]
			},
			"faces": {
				"north": {
					"uv": [
						6.75,
						1.75,
						7.5,
						1.5
					],
					"texture": "#1",
					"tintindex": 0
				},
				"east": {
					"uv": [
						5,
						7.75,
						5.25,
						7.25
					],
					"rotation": 270,
					"texture": "#1",
					"tintindex": 0
				},
				"south": {
					"uv": [
						6.75,
						1.75,
						7.5,
						2
					],
					"rotation": 180,
					"texture": "#1",
					"tintindex": 0
				},
				"west": {
					"uv": [
						5.25,
						7.75,
						5.5,
						7.25
					],
					"rotation": 90,
					"texture": "#1",
					"tintindex": 0
				},
				"up": {
					"uv": [
						6,
						0.5,
						6.75,
						0
					],
					"rotation": 180,
					"texture": "#1",
					"tintindex": 0
				},
				"down": {
					"uv": [
						6,
						1,
						6.75,
						0.5
					],
					"texture": "#1",
					"tintindex": 0
				}
			}
		},
		{
			"from": [
				7.351351351351351,
				8.332232321877203,
				11.371731770125681
			],
			"to": [
				8.64864864864865,
				8.98088097052585,
				12.02038041877433
			],
			"rotation": {
				"angle": -22.5,
				"axis": "x",
				"origin": [
					8,
					9.6295296191745,
					8.939299337693246
				]
			},
			"faces": {
				"north": {
					"uv": [
						6.5,
						7.5,
						7,
						7.25
					],
					"texture": "#1",
					"tintindex": 0
				},
				"east": {
					"uv": [
						6.5,
						7.75,
						6.75,
						7.5
					],
					"rotation": 270,
					"texture": "#1",
					"tintindex": 0
				},
				"south": {
					"uv": [
						7.25,
						6.75,
						7.75,
						7
					],
					"rotation": 180,
					"texture": "#1",
					"tintindex": 0
				},
				"west": {
					"uv": [
						7.5,
						6.75,
						7.75,
						6.5
					],
					"rotation": 90,
					"texture": "#1",
					"tintindex": 0
				},
				"up": {
					"uv": [
						5.5,
						7.5,
						6,
						7.25
					],
					"rotation": 180,
					"texture": "#1",
					"tintindex": 0
				},
				"down": {
					"uv": [
						6,
						7.5,
						6.5,
						7.25
					],
					"texture": "#1",
					"tintindex": 0
				}
			}
		},
		{
			"from": [
				7.027027027027027,
				7.034935024579905,
				10.074434472828383
			],
			"to": [
				8.972972972972974,
				7.683583673228554,
				11.371731770125681
			],
			"rotation": {
				"angle": 22.5,
				"axis": "x",
				"origin": [
					8,
					6.386286375931257,
					8.939299337693246
				]
			},
			"faces": {
				"north": {
					"uv": [
						6.75,
						4,
						7.5,
						3.75
					],
					"texture": "#1",
					"tintindex": 0
				},
				"east": {
					"uv": [
						7,
						7.75,
						7.25,
						7.25
					],
					"rotation": 270,
					"texture": "#1",
					"tintindex": 0
				},
				"south": {
					"uv": [
						4,
						6.75,
						4.75,
						7
					],
					"rotation": 180,
					"texture": "#1",
					"tintindex": 0
				},
				"west": {
					"uv": [
						7.25,
						7.75,
						7.5,
						7.25
					],
					"rotation": 90,
					"texture": "#1",
					"tintindex": 0
				},
				"up": {
					"uv": [
						6,
						1.5,
						6.75,
						1
					],
					"rotation": 180,
					"texture": "#1",
					"tintindex": 0
				},
				"down": {
					"uv": [
						6,
						2,
						6.75,
						1.5
					],
					"texture": "#1",
					"tintindex": 0
				}
			}
		},
		{
			"from": [
				7.351351351351351,
				6.386286375931257,
				10.074434472828383
			],
			"to": [
				8.64864864864865,
				7.034935024579905,
				11.371731770125681
			],
			"rotation": {
				"angle": 22.5,
				"axis": "x",
				"origin": [
					8,
					6.386286375931257,
					8.939299337693246
				]
			},
			"faces": {
				"north": {
					"uv": [
						0.25,
						7.75,
						0.75,
						7.5
					],
					"texture": "#1",
					"tintindex": 0
				},
				"east": {
					"uv": [
						0,
						8,
						0.25,
						7.5
					],
					"rotation": 270,
					"texture": "#1",
					"tintindex": 0
				},
				"south": {
					"uv": [
						7.5,
						0.5,
						8,
						0.75
					],
					"rotation": 180,
					"texture": "#1",
					"tintindex": 0
				},
				"west": {
					"uv": [
						7.5,
						0.5,
						7.75,
						0
					],
					"rotation": 90,
					"texture": "#1",
					"tintindex": 0
				},
				"up": {
					"uv": [
						6.25,
						6,
						6.75,
						5.5
					],
					"rotation": 180,
					"texture": "#1",
					"tintindex": 0
				},
				"down": {
					"uv": [
						6.25,
						6.5,
						6.75,
						6
					],
					"texture": "#1",
					"tintindex": 0
				}
			}
		},
		{
			"from": [
				7.351351351351351,
				7.034935024579905,
				11.371731770125681
			],
			"to": [
				8.64864864864865,
				7.683583673228554,
				12.02038041877433
			],
			"rotation": {
				"angle": 22.5,
				"axis": "x",
				"origin": [
					8,
					6.386286375931257,
					8.939299337693246
				]
			},
			"faces": {
				"north": {
					"uv": [
						7.5,
						1.25,
						8,
						1
					],
					"texture": "#1",
					"tintindex": 0
				},
				"east": {
					"uv": [
						6.75,
						7.75,
						7,
						7.5
					],
					"rotation": 270,
					"texture": "#1",
					"tintindex": 0
				},
				"south": {
					"uv": [
						1.25,
						7.5,
						1.75,
						7.75
					],
					"rotation": 180,
					"texture": "#1",
					"tintindex": 0
				},
				"west": {
					"uv": [
						7.5,
						7.25,
						7.75,
						7
					],
					"rotation": 90,
					"texture": "#1",
					"tintindex": 0
				},
				"up": {
					"uv": [
						0.75,
						7.75,
						1.25,
						7.5
					],
					"rotation": 180,
					"texture": "#1",
					"tintindex": 0
				},
				"down": {
					"uv": [
						7.5,
						1,
						8,
						0.75
					],
					"texture": "#1",
					"tintindex": 0
				}
			}
		},
		{
			"from": [
				7.351351351351351,
				7.034935024579905,
				6.669029067422976
			],
			"to": [
				8.64864864864865,
				7.683583673228554,
				7.317677716071625
			],
			"rotation": {
				"angle": -22.5,
				"axis": "x",
				"origin": [
					8,
					8.007907997552879,
					10.236596634990544
				]
			},
			"faces": {
				"north": {
					"uv": [
						1.75,
						7.75,
						2.25,
						7.5
					],
					"texture": "#1",
					"tintindex": 0
				},
				"east": {
					"uv": [
						7.5,
						7.5,
						7.75,
						7.25
					],
					"rotation": 270,
					"texture": "#1",
					"tintindex": 0
				},
				"south": {
					"uv": [
						7.5,
						1.75,
						8,
						2
					],
					"rotation": 180,
					"texture": "#1",
					"tintindex": 0
				},
				"west": {
					"uv": [
						7.5,
						7.75,
						7.75,
						7.5
					],
					"rotation": 90,
					"texture": "#1",
					"tintindex": 0
				},
				"up": {
					"uv": [
						7.5,
						1.5,
						8,
						1.25
					],
					"rotation": 180,
					"texture": "#1",
					"tintindex": 0
				},
				"down": {
					"uv": [
						7.5,
						1.75,
						8,
						1.5
					],
					"texture": "#1",
					"tintindex": 0
				}
			}
		},
		{
			"from": [
				7.027027027027027,
				7.034935024579905,
				7.317677716071625
			],
			"to": [
				8.972972972972974,
				7.683583673228554,
				9.91227231066622
			],
			"rotation": {
				"angle": -22.5,
				"axis": "x",
				"origin": [
					8,
					8.007907997552879,
					10.236596634990544
				]
			},
			"faces": {
				"north": {
					"uv": [
						6.75,
						4.25,
						7.5,
						4
					],
					"texture": "#1",
					"tintindex": 0
				},
				"east": {
					"uv": [
						0.5,
						7.5,
						0.75,
						6.5
					],
					"rotation": 270,
					"texture": "#1",
					"tintindex": 0
				},
				"south": {
					"uv": [
						6.75,
						4.5,
						7.5,
						4.75
					],
					"rotation": 180,
					"texture": "#1",
					"tintindex": 0
				},
				"west": {
					"uv": [
						0.75,
						7.5,
						1,
						6.5
					],
					"rotation": 90,
					"texture": "#1",
					"tintindex": 0
				},
				"up": {
					"uv": [
						5.25,
						2,
						6,
						1
					],
					"rotation": 180,
					"texture": "#1",
					"tintindex": 0
				},
				"down": {
					"uv": [
						1.25,
						6.25,
						2,
						5.25
					],
					"texture": "#1",
					"tintindex": 0
				}
			}
		},
		{
			"from": [
				7.351351351351351,
				6.386286375931257,
				7.966326364720274
			],
			"to": [
				8.64864864864865,
				7.034935024579905,
				9.91227231066622
			],
			"rotation": {
				"angle": -22.5,
				"axis": "x",
				"origin": [
					8,
					8.007907997552879,
					10.236596634990544
				]
			},
			"faces": {
				"north": {
					"uv": [
						7.5,
						2.25,
						8,
						2
					],
					"texture": "#1",
					"tintindex": 0
				},
				"east": {
					"uv": [
						3,
						7.5,
						3.25,
						6.75
					],
					"rotation": 270,
					"texture": "#1",
					"tintindex": 0
				},
				"south": {
					"uv": [
						7.5,
						2.25,
						8,
						2.5
					],
					"rotation": 180,
					"texture": "#1",
					"tintindex": 0
				},
				"west": {
					"uv": [
						3.25,
						7.5,
						3.5,
						6.75
					],
					"rotation": 90,
					"texture": "#1",
					"tintindex": 0
				},
				"up": {
					"uv": [
						6,
						3.25,
						6.5,
						2.5
					],
					"rotation": 180,
					"texture": "#1",
					"tintindex": 0
				},
				"down": {
					"uv": [
						3,
						6.75,
						3.5,
						6
					],
					"texture": "#1",
					"tintindex": 0
				}
			}
		},
		{
			"from": [
				7.027027027027027,
				6.386286375931257,
				17.047407445801355
			],
			"to": [
				8.972972972972974,
				8.332232321877203,
				17.696056094450007
			],
			"rotation": {
				"angle": -45,
				"axis": "x",
				"origin": [
					8,
					8.007907997552879,
					16.074434472828386
				]
			},
			"faces": {
				"north": {
					"uv": [
						3.75,
						6,
						4.5,
						5.25
					],
					"texture": "#1",
					"tintindex": 0
				},
				"east": {
					"uv": [
						6.75,
						5.25,
						7.5,
						5
					],
					"rotation": 270,
					"texture": "#1",
					"tintindex": 0
				},
				"south": {
					"uv": [
						5.25,
						3.75,
						6,
						4.5
					],
					"rotation": 180,
					"texture": "#1",
					"tintindex": 0
				},
				"west": {
					"uv": [
						6.75,
						5.75,
						7.5,
						5.5
					],
					"rotation": 90,
					"texture": "#1",
					"tintindex": 0
				},
				"up": {
					"uv": [
						6.75,
						5,
						7.5,
						4.75
					],
					"rotation": 180,
					"texture": "#1",
					"tintindex": 0
				},
				"down": {
					"uv": [
						6.75,
						5.5,
						7.5,
						5.25
					],
					"texture": "#1",
					"tintindex": 0
				}
			}
		},
		{
			"from": [
				7.027027027027027,
				6.386286375931257,
				15.75011014850406
			],
			"to": [
				8.972972972972974,
				7.034935024579905,
				17.047407445801355
			],
			"rotation": {
				"angle": -45,
				"axis": "x",
				"origin": [
					8,
					8.007907997552879,
					16.074434472828386
				]
			},
			"faces": {
				"north": {
					"uv": [
						5.75,
						7,
						6.5,
						6.75
					],
					"texture": "#1",
					"tintindex": 0
				},
				"east": {
					"uv": [
						2.25,
						8,
						2.5,
						7.5
					],
					"rotation": 270,
					"texture": "#1",
					"tintindex": 0
				},
				"south": {
					"uv": [
						6.75,
						5.75,
						7.5,
						6
					],
					"rotation": 180,
					"texture": "#1",
					"tintindex": 0
				},
				"west": {
					"uv": [
						3,
						8,
						3.25,
						7.5
					],
					"rotation": 90,
					"texture": "#1",
					"tintindex": 0
				},
				"up": {
					"uv": [
						3.5,
						6.5,
						4.25,
						6
					],
					"rotation": 180,
					"texture": "#1",
					"tintindex": 0
				},
				"down": {
					"uv": [
						6,
						4.25,
						6.75,
						3.75
					],
					"texture": "#1",
					"tintindex": 0
				}
			}
		},
		{
			"from": [
				7.027027027027027,
				7.034935024579905,
				16.39875879715271
			],
			"to": [
				8.972972972972974,
				7.683583673228554,
				17.047407445801355
			],
			"rotation": {
				"angle": -45,
				"axis": "x",
				"origin": [
					8,
					8.007907997552879,
					16.074434472828386
				]
			},
			"faces": {
				"north": {
					"uv": [
						6.5,
						7,
						7.25,
						6.75
					],
					"texture": "#1",
					"tintindex": 0
				},
				"east": {
					"uv": [
						7.75,
						0.25,
						8,
						0
					],
					"rotation": 270,
					"texture": "#1",
					"tintindex": 0
				},
				"south": {
					"uv": [
						7,
						2.5,
						7.75,
						2.75
					],
					"rotation": 180,
					"texture": "#1",
					"tintindex": 0
				},
				"west": {
					"uv": [
						0.25,
						8,
						0.5,
						7.75
					],
					"rotation": 90,
					"texture": "#1",
					"tintindex": 0
				},
				"up": {
					"uv": [
						6.75,
						6.25,
						7.5,
						6
					],
					"rotation": 180,
					"texture": "#1",
					"tintindex": 0
				},
				"down": {
					"uv": [
						6.75,
						6.5,
						7.5,
						6.25
					],
					"texture": "#1",
					"tintindex": 0
				}
			}
		},
		{
			"from": [
				7.351351351351351,
				7.35925934890423,
				11.20956960796352
			],
			"to": [
				8.64864864864865,
				8.656556646201526,
				17.047407445801355
			],
			"rotation": {
				"angle": 0,
				"axis": "y",
				"origin": [
					8,
					8.007907997552879,
					10.560920959314869
				]
			},
			"faces": {
				"north": {
					"uv": [
						1,
						7,
						1.5,
						6.5
					],
					"texture": "#1",
					"tintindex": 0
				},
				"east": {
					"uv": [
						4.75,
						4.5,
						5.25,
						2.25
					],
					"rotation": 270,
					"texture": "#1",
					"tintindex": 0
				},
				"south": {
					"uv": [
						6.5,
						2.5,
						7,
						3
					],
					"rotation": 180,
					"texture": "#1",
					"tintindex": 0
				},
				"west": {
					"uv": [
						0,
						7.5,
						0.5,
						5.25
					],
					"rotation": 90,
					"texture": "#1",
					"tintindex": 0
				},
				"up": {
					"uv": [
						4.75,
						2.25,
						5.25,
						0
					],
					"rotation": 180,
					"texture": "#1",
					"tintindex": 0
				},
				"down": {
					"uv": [
						4.75,
						6.75,
						5.25,
						4.5
					],
					"texture": "#1",
					"tintindex": 0
				}
			}
		},
		{
			"from": [
				7.351351351351351,
				7.034935024579905,
				-4.357997959604051
			],
			"to": [
				8.64864864864865,
				8.98088097052585,
				9.26362366201757
			],
			"rotation": {
				"angle": 0,
				"axis": "y",
				"origin": [
					8,
					8.656556646201526,
					9.91227231066622
				]
			},
			"faces": {
				"north": {
					"uv": [
						4.25,
						6.75,
						4.75,
						6
					],
					"texture": "#1",
					"tintindex": 0
				},
				"east": {
					"uv": [
						0,
						5.25,
						0.75,
						0
					],
					"rotation": 270,
					"texture": "#1",
					"tintindex": 0
				},
				"south": {
					"uv": [
						5.75,
						6,
						6.25,
						6.75
					],
					"rotation": 180,
					"texture": "#1",
					"tintindex": 0
				},
				"west": {
					"uv": [
						0.75,
						5.25,
						1.5,
						0
					],
					"rotation": 90,
					"texture": "#1",
					"tintindex": 0
				},
				"up": {
					"uv": [
						1.5,
						5.25,
						2,
						0
					],
					"rotation": 180,
					"texture": "#1",
					"tintindex": 0
				},
				"down": {
					"uv": [
						2,
						5.25,
						2.5,
						0
					],
					"texture": "#1",
					"tintindex": 0
				}
			}
		},
		{
			"from": [
				7.351351351351351,
				7.683583673228554,
				-5.655295256901347
			],
			"to": [
				8.64864864864865,
				8.332232321877203,
				-4.357997959604051
			],
			"rotation": {
				"angle": 0,
				"axis": "y",
				"origin": [
					8,
					8.007907997552879,
					-3.0607006623067523
				]
			},
			"faces": {
				"north": {
					"uv": [
						7.5,
						3,
						8,
						2.75
					],
					"texture": "#1",
					"tintindex": 0
				},
				"east": {
					"uv": [
						3.25,
						8,
						3.5,
						7.5
					],
					"rotation": 270,
					"texture": "#1",
					"tintindex": 0
				},
				"south": {
					"uv": [
						7.5,
						3.75,
						8,
						4
					],
					"rotation": 180,
					"texture": "#1",
					"tintindex": 0
				},
				"west": {
					"uv": [
						7.5,
						3.75,
						7.75,
						3.25
					],
					"rotation": 90,
					"texture": "#1",
					"tintindex": 0
				},
				"up": {
					"uv": [
						3.5,
						7,
						4,
						6.5
					],
					"rotation": 180,
					"texture": "#1",
					"tintindex": 0
				},
				"down": {
					"uv": [
						5.25,
						7,
						5.75,
						6.5
					],
					"texture": "#1",
					"tintindex": 0
				}
			}
		},
		{
			"from": [
				7.675675675675675,
				8.98088097052585,
				-4.357997959604051
			],
			"to": [
				8.324324324324325,
				9.6295296191745,
				9.26362366201757
			],
			"rotation": {
				"angle": 0,
				"axis": "y",
				"origin": [
					8,
					8.007907997552879,
					10.560920959314869
				]
			},
			"faces": {
				"north": {
					"uv": [
						7.75,
						0.5,
						8,
						0.25
					],
					"texture": "#1",
					"tintindex": 0
				},
				"east": {
					"uv": [
						3.5,
						5.25,
						3.75,
						0
					],
					"rotation": 270,
					"texture": "#1",
					"tintindex": 0
				},
				"south": {
					"uv": [
						0.5,
						7.75,
						0.75,
						8
					],
					"rotation": 180,
					"texture": "#1",
					"tintindex": 0
				},
				"west": {
					"uv": [
						4,
						5.25,
						4.25,
						0
					],
					"rotation": 90,
					"texture": "#1",
					"tintindex": 0
				},
				"up": {
					"uv": [
						3.25,
						5.25,
						3.5,
						0
					],
					"rotation": 180,
					"texture": "#1",
					"tintindex": 0
				},
				"down": {
					"uv": [
						3.75,
						5.25,
						4,
						0
					],
					"texture": "#1",
					"tintindex": 0
				}
			}
		},
		{
			"from": [
				7.675675675675675,
				7.683583673228554,
				-6.303943905549998
			],
			"to": [
				8.324324324324325,
				8.332232321877203,
				-5.655295256901347
			],
			"rotation": {
				"angle": 0,
				"axis": "y",
				"origin": [
					8,
					8.007907997552879,
					6.669029067422976
				]
			},
			"faces": {
				"north": {
					"uv": [
						1.75,
						8,
						2,
						7.75
					],
					"texture": "#1",
					"tintindex": 0
				},
				"east": {
					"uv": [
						1,
						8,
						1.25,
						7.75
					],
					"rotation": 270,
					"texture": "#1",
					"tintindex": 0
				},
				"south": {
					"uv": [
						2,
						7.75,
						2.25,
						8
					],
					"rotation": 180,
					"texture": "#1",
					"tintindex": 0
				},
				"west": {
					"uv": [
						1.5,
						8,
						1.75,
						7.75
					],
					"rotation": 90,
					"texture": "#1",
					"tintindex": 0
				},
				"up": {
					"uv": [
						0.75,
						8,
						1,
						7.75
					],
					"rotation": 180,
					"texture": "#1",
					"tintindex": 0
				},
				"down": {
					"uv": [
						1.25,
						8,
						1.5,
						7.75
					],
					"texture": "#1",
					"tintindex": 0
				}
			}
		},
		{
			"from": [
				7.675675675675675,
				8.332232321877203,
				-5.655295256901347
			],
			"to": [
				8.324324324324325,
				8.98088097052585,
				-4.357997959604051
			],
			"rotation": {
				"angle": 0,
				"axis": "y",
				"origin": [
					8,
					8.007907997552879,
					6.669029067422976
				]
			},
			"faces": {
				"north": {
					"uv": [
						7.75,
						2.75,
						8,
						2.5
					],
					"texture": "#1",
					"tintindex": 0
				},
				"east": {
					"uv": [
						7.5,
						4.5,
						7.75,
						4
					],
					"rotation": 270,
					"texture": "#1",
					"tintindex": 0
				},
				"south": {
					"uv": [
						7.75,
						3,
						8,
						3.25
					],
					"rotation": 180,
					"texture": "#1",
					"tintindex": 0
				},
				"west": {
					"uv": [
						4.5,
						8,
						4.75,
						7.5
					],
					"rotation": 90,
					"texture": "#1",
					"tintindex": 0
				},
				"up": {
					"uv": [
						4,
						8,
						4.25,
						7.5
					],
					"rotation": 180,
					"texture": "#1",
					"tintindex": 0
				},
				"down": {
					"uv": [
						4.25,
						8,
						4.5,
						7.5
					],
					"texture": "#1",
					"tintindex": 0
				}
			}
		},
		{
			"from": [
				7.675675675675675,
				6.386286375931257,
				-4.357997959604051
			],
			"to": [
				8.324324324324325,
				7.034935024579905,
				9.26362366201757
			],
			"rotation": {
				"angle": 0,
				"axis": "y",
				"origin": [
					8,
					8.007907997552879,
					10.560920959314869
				]
			},
			"faces": {
				"north": {
					"uv": [
						7.75,
						3.5,
						8,
						3.25
					],
					"texture": "#1",
					"tintindex": 0
				},
				"east": {
					"uv": [
						4.5,
						5.25,
						4.75,
						0
					],
					"rotation": 270,
					"texture": "#1",
					"tintindex": 0
				},
				"south": {
					"uv": [
						3.5,
						7.75,
						3.75,
						8
					],
					"rotation": 180,
					"texture": "#1",
					"tintindex": 0
				},
				"west": {
					"uv": [
						2.75,
						9.75,
						3,
						4.5
					],
					"rotation": 90,
					"texture": "#1",
					"tintindex": 0
				},
				"up": {
					"uv": [
						4.25,
						5.25,
						4.5,
						0
					],
					"rotation": 180,
					"texture": "#1",
					"tintindex": 0
				},
				"down": {
					"uv": [
						2.5,
						9.75,
						2.75,
						4.5
					],
					"texture": "#1",
					"tintindex": 0
				}
			}
		},
		{
			"from": [
				7.675675675675675,
				7.034935024579905,
				-5.655295256901347
			],
			"to": [
				8.324324324324325,
				7.683583673228554,
				-4.357997959604051
			],
			"rotation": {
				"angle": 0,
				"axis": "y",
				"origin": [
					8,
					8.007907997552879,
					6.669029067422976
				]
			},
			"faces": {
				"north": {
					"uv": [
						7.75,
						3.75,
						8,
						3.5
					],
					"texture": "#1",
					"tintindex": 0
				},
				"east": {
					"uv": [
						4.75,
						8,
						5,
						7.5
					],
					"rotation": 270,
					"texture": "#1",
					"tintindex": 0
				},
				"south": {
					"uv": [
						3.75,
						7.75,
						4,
						8
					],
					"rotation": 180,
					"texture": "#1",
					"tintindex": 0
				},
				"west": {
					"uv": [
						5.5,
						8,
						5.75,
						7.5
					],
					"rotation": 90,
					"texture": "#1",
					"tintindex": 0
				},
				"up": {
					"uv": [
						7.5,
						5,
						7.75,
						4.5
					],
					"rotation": 180,
					"texture": "#1",
					"tintindex": 0
				},
				"down": {
					"uv": [
						7.5,
						5.5,
						7.75,
						5
					],
					"texture": "#1",
					"tintindex": 0
				}
			}
		}
	],
	"display": {
		"head": {
			"rotation": [
				0,
				180,
				0
			]
		}
	}
}