{
	"textures": {
		"1": "animated_java:blueprint/twins_rubiel/rubiel_katana",
		"particle": "minecraft:item/pufferfish"
	},
	"display": {
		"head": {
			"rotation": [0, 180, 0]
		}
	},
	"elements": [
		{
			"from": [7.53264, 7.59055, 13.96127],
			"to": [9.2004, 8.61195, 23.13036],
			"rotation": {
				"angle": 0,
				"axis": "y",
				"origin": [-0.70496, 3.92211, 22.91976]
			},
			"faces": {
				"north": {
					"uv": [7, 0, 7.375, 0.125],
					"texture": "#1"
				},
				"east": {
					"uv": [7, 0, 7.375, 0.125],
					"texture": "#1"
				},
				"south": {
					"uv": [7, 0, 7.375, 0.125],
					"texture": "#1"
				},
				"west": {
					"uv": [7, 0, 7.375, 0.125],
					"texture": "#1"
				},
				"up": {
					"uv": [7, 0, 7.375, 0.125],
					"texture": "#1"
				},
				"down": {
					"uv": [7, 0, 7.375, 0.125],
					"texture": "#1"
				}
			}
		},
		{
			"from": [7.0677, 7.59055, 1.72233],
			"to": [8.73547, 8.61195, 5.19921],
			"rotation": {
				"angle": 0,
				"axis": "y",
				"origin": [-0.70496, 3.92211, 22.91976]
			},
			"faces": {
				"north": {
					"uv": [7, 0, 7.375, 0.125],
					"texture": "#1"
				},
				"east": {
					"uv": [7, 0, 7.375, 0.125],
					"texture": "#1"
				},
				"south": {
					"uv": [7, 0, 7.375, 0.125],
					"texture": "#1"
				},
				"west": {
					"uv": [7, 0, 7.375, 0.125],
					"texture": "#1"
				},
				"up": {
					"uv": [7, 0, 7.375, 0.125],
					"texture": "#1"
				},
				"down": {
					"uv": [7, 0, 7.375, 0.125],
					"texture": "#1"
				}
			}
		},
		{
			"from": [6.80445, 7.59055, -0.86964],
			"to": [8.47222, 8.61195, 1.71625],
			"rotation": {
				"angle": 0,
				"axis": "y",
				"origin": [-0.70496, 3.92211, 22.91976]
			},
			"faces": {
				"north": {
					"uv": [7, 0, 7.375, 0.125],
					"texture": "#1"
				},
				"east": {
					"uv": [7, 0, 7.375, 0.125],
					"texture": "#1"
				},
				"south": {
					"uv": [7, 0, 7.375, 0.125],
					"texture": "#1"
				},
				"west": {
					"uv": [7, 0, 7.375, 0.125],
					"texture": "#1"
				},
				"up": {
					"uv": [7, 0, 7.375, 0.125],
					"texture": "#1"
				},
				"down": {
					"uv": [7, 0, 7.375, 0.125],
					"texture": "#1"
				}
			}
		},
		{
			"from": [7.25967, 7.59055, 5.17896],
			"to": [8.92744, 8.61195, 13.96127],
			"rotation": {
				"angle": 0,
				"axis": "y",
				"origin": [-0.70496, 3.92211, 22.91976]
			},
			"faces": {
				"north": {
					"uv": [7, 0, 7.375, 0.125],
					"texture": "#1"
				},
				"east": {
					"uv": [7, 0, 7.375, 0.125],
					"texture": "#1"
				},
				"south": {
					"uv": [7, 0, 7.375, 0.125],
					"texture": "#1"
				},
				"west": {
					"uv": [7, 0, 7.375, 0.125],
					"texture": "#1"
				},
				"up": {
					"uv": [7, 0, 7.375, 0.125],
					"texture": "#1"
				},
				"down": {
					"uv": [7, 0, 7.375, 0.125],
					"texture": "#1"
				}
			}
		}
	]
}