{
	"textures": {
		"0": "animated_java:item/twins_rubiel/rubiel"
	},
	"display": {
		"head": {
			"rotation": [0, 180, 0]
		}
	},
	"elements": [
		{
			"from": [6.875, 6.875, 7.6],
			"to": [9.15, 9.125, 12.6],
			"rotation": {
				"angle": 0,
				"axis": "y",
				"origin": [8, 8, 8.1]
			},
			"faces": {
				"north": {
					"uv": [8.5, 14.375, 8.75, 14.625],
					"texture": "#0"
				},
				"east": {
					"uv": [7.875, 14.375, 8.5, 14.625],
					"texture": "#0"
				},
				"south": {
					"uv": [9.375, 14.375, 9.625, 14.625],
					"texture": "#0"
				},
				"west": {
					"uv": [8.75, 14.375, 9.375, 14.625],
					"texture": "#0"
				},
				"up": {
					"uv": [8.75, 14.375, 8.5, 13.75],
					"texture": "#0"
				},
				"down": {
					"uv": [9, 13.75, 8.75, 14.375],
					"texture": "#0"
				}
			}
		}
	]
}