{
	"parent": "item/generated",
	"textures": {
		"layer0": "minecraft:item/explorer_pottery_sherd"
	},
	"overrides": [
		{
			"predicate": {
				"custom_model_data": 1
			},
			"model": "animated_java:empty"
		},
		{
			"predicate": {
				"custom_model_data": 2
			},
			"model": "animated_java:blueprint/convict/left_leg"
		},
		{
			"predicate": {
				"custom_model_data": 3
			},
			"model": "animated_java:blueprint/convict/left_leg_2"
		},
		{
			"predicate": {
				"custom_model_data": 4
			},
			"model": "animated_java:blueprint/convict/right_leg"
		},
		{
			"predicate": {
				"custom_model_data": 5
			},
			"model": "animated_java:blueprint/convict/right_leg_2"
		},
		{
			"predicate": {
				"custom_model_data": 6
			},
			"model": "animated_java:blueprint/convict/body"
		},
		{
			"predicate": {
				"custom_model_data": 7
			},
			"model": "animated_java:blueprint/convict/head"
		},
		{
			"predicate": {
				"custom_model_data": 8
			},
			"model": "animated_java:blueprint/convict/left_arm"
		},
		{
			"predicate": {
				"custom_model_data": 9
			},
			"model": "animated_java:blueprint/convict/left_arm_2"
		},
		{
			"predicate": {
				"custom_model_data": 10
			},
			"model": "animated_java:blueprint/convict/left_axe"
		},
		{
			"predicate": {
				"custom_model_data": 11
			},
			"model": "animated_java:blueprint/convict/right_arm"
		},
		{
			"predicate": {
				"custom_model_data": 12
			},
			"model": "animated_java:blueprint/convict/right_arm_2"
		},
		{
			"predicate": {
				"custom_model_data": 13
			},
			"model": "animated_java:blueprint/convict/right_axe"
		}
	],
	"animated_java": {
		"convict": [1, 2, 3, 4, 5, 6, 7, 8, 9, 10, 11, 12, 13]
	}
}