{
    "parent": "item/generated",
    "textures": {
        "layer0": "item/leather_horse_armor"
    },
    "overrides": [
        {
            "predicate": {
                "custom_model_data": 20083
            },
            "model": "item/other/leather_horse_armor/20083"
        },
        {
            "predicate": {
                "custom_model_data": 20084
            },
            "model": "item/other/leather_horse_armor/20084"
        },
        {
            "predicate": {
                "custom_model_data": 20085
            },
            "model": "item/other/leather_horse_armor/20085"
        },
        {
            "predicate": {
                "custom_model_data": 20086
            },
            "model": "item/other/leather_horse_armor/20086"
        },
        {
            "predicate": {
                "custom_model_data": 20087
            },
            "model": "item/leather_horse_armor"
        },
        {
            "predicate": {
                "custom_model_data": 20138
            },
            "model": "item/mob/leather_horse_armor/20138"
        },
        {
            "predicate": {
                "custom_model_data": 20139
            },
            "model": "item/leather_horse_armor"
        },
        {
            "predicate": {
                "custom_model_data": 20334
            },
            "model": "item/other/leather_horse_armor/20334"
        },
        {
            "predicate": {
                "custom_model_data": 20335
            },
            "model": "item/leather_horse_armor"
        },
        {
            "predicate": {
                "custom_model_data": 20352
            },
            "model": "item/other/leather_horse_armor/20352"
        },
        {
            "predicate": {
                "custom_model_data": 20353
            },
            "model": "item/other/leather_horse_armor/20353"
        },
        {
            "predicate": {
                "custom_model_data": 20354
            },
            "model": "item/other/leather_horse_armor/20354"
        },
        {
            "predicate": {
                "custom_model_data": 20355
            },
            "model": "item/other/leather_horse_armor/20355"
        },
        {
            "predicate": {
                "custom_model_data": 20356
            },
            "model": "item/other/leather_horse_armor/20356"
        },
        {
            "predicate": {
                "custom_model_data": 20357
            },
            "model": "item/other/leather_horse_armor/20357"
        },
        {
            "predicate": {
                "custom_model_data": 20358
            },
            "model": "item/other/leather_horse_armor/20358"
        },
        {
            "predicate": {
                "custom_model_data": 20359
            },
            "model": "item/other/leather_horse_armor/20359"
        },
        {
            "predicate": {
                "custom_model_data": 20360
            },
            "model": "item/other/leather_horse_armor/20360"
        },
        {
            "predicate": {
                "custom_model_data": 20361
            },
            "model": "item/other/leather_horse_armor/20361"
        },
        {
            "predicate": {
                "custom_model_data": 20362
            },
            "model": "item/other/leather_horse_armor/20362"
        },
        {
            "predicate": {
                "custom_model_data": 20363
            },
            "model": "item/leather_horse_armor"
        },
        {
            "predicate": {
                "custom_model_data": 20370
            },
            "model": "item/other/leather_horse_armor/20370"
        },
        {
            "predicate": {
                "custom_model_data": 20371
            },
            "model": "item/leather_horse_armor"
        },
        {
            "predicate": {
                "custom_model_data": 20375
            },
            "model": "item/other/leather_horse_armor/20375"
        },
        {
            "predicate": {
                "custom_model_data": 20376
            },
            "model": "item/other/leather_horse_armor/20376"
        },
        {
            "predicate": {
                "custom_model_data": 20377
            },
            "model": "item/other/leather_horse_armor/20377"
        },
        {
            "predicate": {
                "custom_model_data": 20378
            },
            "model": "item/leather_horse_armor"
        },
        {
            "predicate": {
                "custom_model_data": 20379
            },
            "model": "item/other/leather_horse_armor/20379"
        },
        {
            "predicate": {
                "custom_model_data": 20380
            },
            "model": "item/other/leather_horse_armor/20380"
        },
        {
            "predicate": {
                "custom_model_data": 20381
            },
            "model": "item/other/leather_horse_armor/20381"
        },
        {
            "predicate": {
                "custom_model_data": 20382
            },
            "model": "item/other/leather_horse_armor/20382"
        },
        {
            "predicate": {
                "custom_model_data": 20383
            },
            "model": "item/other/leather_horse_armor/20383"
        },
        {
            "predicate": {
                "custom_model_data": 20384
            },
            "model": "item/leather_horse_armor"
        },
        {
            "predicate": {
                "custom_model_data": 20396
            },
            "model": "item/other/leather_horse_armor/20396"
        },
        {
            "predicate": {
                "custom_model_data": 20397
            },
            "model": "item/mob/leather_horse_armor/20397"
        },
        {
            "predicate": {
                "custom_model_data": 20398
            },
            "model": "item/leather_horse_armor"
        }
    ]
}